sbomaudit/__init__.py
sbomaudit/audit.py
sbomaudit/cli.py
sbomaudit/version.py
sbomaudit-0.4.4.dist-info/LICENSE
sbomaudit-0.4.4.dist-info/METADATA
sbomaudit-0.4.4.dist-info/WHEEL
sbomaudit-0.4.4.dist-info/entry_points.txt
sbomaudit-0.4.4.dist-info/top_level.txt
sbomaudit-0.4.4.dist-info/RECORD
